{
  "end_date": "1862-06-30",
  "casualties": 500,
  "casualties_text": "500 total",
  "forces": {
    "Confederate": {
      "commanders": [
        {
          "rank": "Major General",
          "first_name": "Thomas",
          "suffix": "",
          "navy": false,
          "middle_name": "J.",
          "last_name": "Jackson",
          "fullname": "Thomas J. Jackson"
        }
      ],
      "armies": 1
    },
    "US": {
      "commanders": [
        {
          "rank": "Major General",
          "first_name": "William",
          "suffix": "",
          "navy": false,
          "middle_name": "B.",
          "last_name": "Franklin",
          "fullname": "William B. Franklin"
        }
      ],
      "armies": 1
    }
  },
  "cwsac_reference": "VA020a",
  "operation": false,
  "forces_text": "Armies",
  "start_date": "1862-06-30",
  "preservation": "II.3",
  "results_text": "Inconclusive",
  "description": "The Union rearguard under Maj. Gen. William Franklin stopped Jackson's divisions at the White Oak Bridge crossing, resulting in an artillery duel, while the main battle raged two miles farther south at Glendale or Frayser's Farm. White Oak Swamp can be considered part of the Glendale engagement.",
  "state": "VA",
  "significance": "C",
  "other_names": null,
  "dates": "June 30, 1862",
  "battle_name": "White Oak Swamp",
  "principal_commanders": "Maj. Gen. William B. Franklin [US]; Maj. Gen. Thomas J. Jackson [CS]",
  "campaign": "Peninsula Campaign [March-July 1862]",
  "belligerents": {
    "Confederate": {
      "commanders": [
        {
          "rank": "Major General",
          "first_name": "Thomas",
          "suffix": "",
          "navy": false,
          "middle_name": "J.",
          "last_name": "Jackson",
          "fullname": "Thomas J. Jackson"
        }
      ],
      "armies": 1
    },
    "US": {
      "commanders": [
        {
          "rank": "Major General",
          "first_name": "William",
          "suffix": "",
          "navy": false,
          "middle_name": "B.",
          "last_name": "Franklin",
          "fullname": "William B. Franklin"
        }
      ],
      "armies": 1
    },
    "CS": {
      "commanders": [
        {
          "rank": "Major General",
          "first_name": "Thomas",
          "suffix": "",
          "navy": false,
          "middle_name": "J.",
          "last_name": "Jackson",
          "fullname": "Thomas J. Jackson"
        }
      ],
      "armies": 1
    }
  },
  "result": "Inconclusive",
  "battle": "VA020A",
  "location": [
    {
      "state": "VA",
      "place": "Henrico County"
    }
  ],
  "url": "http://www.nps.gov/hps/abpp/battles/va020a.htm"
}